busiagptservice/__init__.py
busiagptservice/errors.py
busiagptservice-0.1.0.dist-info/METADATA
busiagptservice-0.1.0.dist-info/WHEEL
busiagptservice-0.1.0.dist-info/top_level.txt
busiagptservice-0.1.0.dist-info/RECORD
