Metadata-Version: 2.1
Name: busiagptservice
Version: 0.1.0
Summary: A simple Python library to interact with GPTs models
Home-page: https://github.com/MakordDEV/BusiaGPTService
Author: MakordDEV
Author-email: makordikrom@gmail.com
Classifier: Programming Language :: Python :: 3
Classifier: License :: OSI Approved :: MIT License
Classifier: Operating System :: OS Independent
Requires-Python: >=3.6
Requires-Dist: requests
